yabc/__init__.py
yabc/__main__.py
yabc/basis.py
yabc/coinpool.py
yabc/costbasisreport.py
yabc/csv_to_json.py
yabc/ohlcprovider.py
yabc/price_data.py
yabc/taxdoc.py
yabc/transaction.py
yabc/transaction_parser.py
yabc/user.py
yabc/version.py
yabc/app/__init__.py
yabc/app/__main__.py
yabc/formats/__init__.py
yabc/formats/adhoc.py
yabc/formats/binance.py
yabc/formats/bitmex.py
yabc/formats/bybit.py
yabc/formats/coinbase.py
yabc/formats/coinbasepro.py
yabc/formats/coinbasettr.py
yabc/formats/formatbase.py
yabc/formats/gemini.py
yabc/formats/localbitcoins.py
yabc/server/__init__.py
yabc/server/inmemory_backend.py
yabc/server/server.py
yabc/server/sql_backend.py
yabc/server/yabc_api.py
yabc/sql/Schema_1to2.py
yabc/sql/Schema_2to3.py
yabc/sql/__init__.py
yabc-0.1.22.dist-info/LICENSE
yabc-0.1.22.dist-info/METADATA
yabc-0.1.22.dist-info/WHEEL
yabc-0.1.22.dist-info/top_level.txt
yabc-0.1.22.dist-info/RECORD
