Metadata-Version: 2.1
Name: yabc
Version: 0.1.22
Summary: A tax estimator for cryptocurrencies.
Home-page: https://github.com/robertkarl/yabc
Author: Robert Karl
Maintainer: Robert Karl
Maintainer-email: robertkarljr@gmail.com
License: UNKNOWN
Platform: UNKNOWN
Classifier: Development Status :: 2 - Pre-Alpha
Classifier: License :: OSI Approved :: MIT License
Classifier: Operating System :: OS Independent
Classifier: Programming Language :: Python
Classifier: Programming Language :: Python :: 3
Classifier: Programming Language :: Python :: 3.5
Classifier: Programming Language :: Python :: 3.6
Classifier: Programming Language :: Python :: 3.7
Classifier: Programming Language :: Python :: 3.8
Classifier: Programming Language :: Python :: 3 :: Only
Requires-Python: >=3.5,<3.9
Requires-Dist: delorean (==1.0.0)
Requires-Dist: flask (==1.1.1)
Requires-Dist: openpyxl
Requires-Dist: python-dateutil (==2.8.0)
Requires-Dist: sqlalchemy (==1.3.3)
